.coveragerc
.travis.yml
AUTHORS.rst
CHANGES.rst
CONTRIBUTING.rst
INSTALL.rst
LICENSE.txt
README.rst
requirements.txt
setup.cfg
setup.py
test-requirements.txt
tox.ini
docs/Makefile
docs/authors.rst
docs/changes.rst
docs/conf.py
docs/index.rst
docs/license.rst
docs/_static/.gitignore
git_explode/__init__.py
git_explode/cli.py
git_explode/exploder.py
git_explode/fragment.py
git_explode/gitutils.py
git_explode/listener.py
git_explode/topics.py
git_explode.egg-info/PKG-INFO
git_explode.egg-info/SOURCES.txt
git_explode.egg-info/dependency_links.txt
git_explode.egg-info/entry_points.txt
git_explode.egg-info/not-zip-safe
git_explode.egg-info/requires.txt
git_explode.egg-info/top_level.txt
tests/conftest.py
tests/test_exploder.py
tests/travis_install.sh