Metadata-Version: 1.1
Name: git-explode
Version: 0.0.1
Summary: Explode linear sequence of commits into topic branches
Home-page: https://github.com/aspiers/git-explode
Author: Adam Spiers
Author-email: git@adamspiers.org
License: GPL-2+
Platform: UNKNOWN
Classifier: Development Status :: 4 - Beta
Classifier: Environment :: Console
Classifier: Intended Audience :: Developers
Classifier: License :: OSI Approved :: GNU General Public License v2 or later (GPLv2+)
Classifier: Natural Language :: English
Classifier: Operating System :: OS Independent
Classifier: Programming Language :: Python
Classifier: Topic :: Software Development :: Version Control
Classifier: Topic :: Utilities
